.DS_Store
stargateRL/__init__.py
stargateRL/__main__.py
stargateRL/utils.py
stargateRL/engine/__init__.py
stargateRL/engine/graphx.py
stargateRL/engine/objects.py
stargateRL/engine/screen.py
stargateRL/engine/widgets.py
stargateRL/entity/__init__.py
stargateRL/launcher/__init__.py
stargateRL/launcher/__main__.py
stargateRL/launcher/elements.py
stargateRL/mapset/__init__.py
stargateRL-0.0.2.data/data/bins/icon.png
stargateRL-0.0.2.data/data/bins/tileset.png
stargateRL-0.0.2.data/data/config/config.json
stargateRL-0.0.2.dist-info/DESCRIPTION.rst
stargateRL-0.0.2.dist-info/METADATA
stargateRL-0.0.2.dist-info/RECORD
stargateRL-0.0.2.dist-info/WHEEL
stargateRL-0.0.2.dist-info/entry_points.txt
stargateRL-0.0.2.dist-info/metadata.json
stargateRL-0.0.2.dist-info/top_level.txt
