Metadata-Version: 2.0
Name: stargateRL
Version: 0.0.2
Summary: A sci-fi rouge-like game, developed in Python using Pyglet.
Home-page: https://github.com/thee-engineer/stargateRL
Author: Alexandru-Paul Copil (thee-engineer)
Author-email: alexandru.p.copil@gmail.com
License: Modified Simple Machine License
Keywords: stargateRL stargate scifi sci-fi rouge-like rougelike game
Platform: UNKNOWN
Classifier: Development Status :: 1 - Planning
Classifier: Intended Audience :: Other Audience
Classifier: Intended Audience :: End Users/Desktop
Classifier: Intended Audience :: Developers
Classifier: Topic :: Games/Entertainment
Classifier: Topic :: Multimedia :: Graphics
Classifier: Environment :: X11 Applications
Classifier: Environment :: MacOS X
Classifier: Environment :: Win32 (MS Windows)
Classifier: License :: Other/Proprietary License
Classifier: Natural Language :: English
Classifier: Programming Language :: Python :: 2.7
Classifier: Programming Language :: Python :: 3.6
